[
  {
    "keyword": "汽車鑰匙遺失",
    "rank": "待實現實際 API",
    "checked_at": "2026-02-26T08:38:38.082458"
  },
  {
    "keyword": "賓士全丟救援",
    "rank": "待實現實際 API",
    "checked_at": "2026-02-26T08:38:38.082465"
  },
  {
    "keyword": "BMW 晶片鑰匙",
    "rank": "待實現實際 API",
    "checked_at": "2026-02-26T08:38:38.082467"
  },
  {
    "keyword": "福特汽車鑰匙配製",
    "rank": "待實現實際 API",
    "checked_at": "2026-02-26T08:38:38.082469"
  },
  {
    "keyword": "Skoda 鑰匙全丟",
    "rank": "待實現實際 API",
    "checked_at": "2026-02-26T08:38:38.082470"
  }
]